README.md
setup.py
mengdodo/__init__.py
mengdodo.egg-info/PKG-INFO
mengdodo.egg-info/SOURCES.txt
mengdodo.egg-info/dependency_links.txt
mengdodo.egg-info/top_level.txt