Metadata-Version: 2.1
Name: mengdodo
Version: 0.1
Summary: 这里是mengdodo的描述
Home-page: http://mengdodo.com
Author: mengdodo
Author-email: losted.dreamer@gmail.com
License: UNKNOWN
Platform: UNKNOWN
Classifier: Programming Language :: Python :: 3
Classifier: License :: OSI Approved :: MIT License
Classifier: Operating System :: OS Independent
